pfeed/__init__.py
pfeed/_etl/base.py
pfeed/_etl/market.py
pfeed/_etl/news.py
pfeed/_io/base_io.py
pfeed/_io/tabular_io.py
pfeed/bytewax_connectors/sources/exchange_source.py
pfeed/cli/__init__.py
pfeed/cli/commands/__init__.py
pfeed/cli/commands/clear.py
pfeed/cli/commands/config.py
pfeed/cli/commands/data/__init__.py
pfeed/cli/commands/data/collectors/__init__.py
pfeed/cli/commands/data/collectors/base.py
pfeed/cli/commands/data/collectors/duckdb.py
pfeed/cli/commands/data/collectors/local.py
pfeed/cli/commands/data/collectors/minio.py
pfeed/cli/commands/data/command.py
pfeed/cli/commands/data/formatters.py
pfeed/cli/commands/data/models.py
pfeed/cli/commands/data/parsers/__init__.py
pfeed/cli/commands/data/parsers/base.py
pfeed/cli/commands/data/parsers/generic.py
pfeed/cli/commands/data/parsers/market_data.py
pfeed/cli/commands/data/parsers/news_data.py
pfeed/cli/commands/deltalake.py
pfeed/cli/commands/doc.py
pfeed/cli/commands/docker_compose.py
pfeed/cli/commands/download.py
pfeed/cli/commands/stream.py
pfeed/cli/main.py
pfeed/cli/utils.py
pfeed/config.py
pfeed/const/aliases.py
pfeed/const/paths.py
pfeed/data_handlers/__init__.py
pfeed/data_handlers/base_data_handler.py
pfeed/data_handlers/market_data_handler.py
pfeed/data_handlers/news_data_handler.py
pfeed/data_handlers/time_based_data_handler.py
pfeed/data_models/__init__.py
pfeed/data_models/base_data_model.py
pfeed/data_models/economics_data_model.py
pfeed/data_models/market_data_model.py
pfeed/data_models/news_data_model.py
pfeed/data_models/pfund_data_model.py
pfeed/data_models/time_based_data_model.py
pfeed/enums/__init__.py
pfeed/enums/data_access_type.py
pfeed/enums/data_category.py
pfeed/enums/data_layer.py
pfeed/enums/data_provider_type.py
pfeed/enums/data_source.py
pfeed/enums/data_storage.py
pfeed/enums/data_tool.py
pfeed/enums/data_type.py
pfeed/enums/env.py
pfeed/enums/extract_type.py
pfeed/feeds/__init__.py
pfeed/feeds/analyst_feed.py
pfeed/feeds/base_feed.py
pfeed/feeds/binance/binance.py
pfeed-0.0.5.dist-info/LICENSE
pfeed-0.0.5.dist-info/METADATA
pfeed-0.0.5.dist-info/WHEEL
pfeed-0.0.5.dist-info/entry_points.txt
pfeed-0.0.5.dist-info/RECORD
