Metadata-Version: 2.3
Name: pfeed
Version: 0.0.5
Summary: Data pipeline for algo-trading, getting and storing both real-time and historical data made easy.
License: Apache-2.0
Keywords: trading,algo-trading,data pipeline,ETL,data lake,data warehouse,data integration,historical data,live data,data streaming,data engineering
Author: Stephen Yau
Author-email: softwareentrepreneer+pfeed@gmail.com
Requires-Python: >=3.10
Classifier: Operating System :: OS Independent
Classifier: Intended Audience :: Developers
Classifier: Intended Audience :: Science/Research
Classifier: Intended Audience :: Financial and Insurance Industry
Classifier: Intended Audience :: Information Technology
Classifier: Topic :: Office/Business :: Financial
Classifier: Topic :: Office/Business :: Financial :: Investment
Classifier: Topic :: Software Development :: Libraries
Classifier: Programming Language :: Python :: 3.10
Classifier: Programming Language :: Python :: 3.11
Classifier: Programming Language :: Python :: 3.12
Classifier: Programming Language :: Python :: 3.13
Provides-Extra: core
Provides-Extra: dask
Provides-Extra: databento
Provides-Extra: fmp
Provides-Extra: spark
Requires-Dist: beautifulsoup4 (>=4.13.3,<5.0.0)
Requires-Dist: bytewax (>=0.21.1,<0.22.0) ; extra == "core"
Requires-Dist: cloudpathlib[azure,gs,s3] (>=0.21.0,<0.22.0) ; extra == "core"
Requires-Dist: coiled (>=1.89.0,<2.0.0) ; extra == "dask"
Requires-Dist: confluent-kafka (>=2.8.2,<3.0.0) ; extra == "core"
Requires-Dist: dask[complete,dataframe] (>=2025.3.0,<2026.0.0) ; extra == "dask"
Requires-Dist: databento (>=0.50.0,<0.51.0) ; (python_version < "4.0.0") and (extra == "databento")
Requires-Dist: deltalake (>=0.25.5,<0.26.0) ; extra == "core"
Requires-Dist: duckdb (>=1.2.2,<2.0.0)
Requires-Dist: fmp-api-client (>=0.0.1,<0.1.0) ; extra == "fmp"
Requires-Dist: minio (>=7.2.15,<8.0.0) ; extra == "core"
Requires-Dist: narwhals (>=1.35.0,<2.0.0)
Requires-Dist: pandas (>=2.2.3,<3.0.0)
Requires-Dist: pandera (>=0.23.1,<0.24.0)
Requires-Dist: pfund (>=0.0.2,<0.1.0)
Requires-Dist: polars (>=1.27.1,<2.0.0)
Requires-Dist: prefect (>=3.3.4,<4.0.0) ; (python_version < "3.14.0") and (extra == "core")
Requires-Dist: pyarrow (>=18.0.0,<19.0.0)
Requires-Dist: pydantic (>=2.11.3,<3.0.0)
Requires-Dist: pyspark[connect,pandas-on-spark,sql] (>=3.5.3,<4.0.0) ; extra == "spark"
Requires-Dist: ray (>=2.44.1,<3.0.0) ; extra == "core"
Requires-Dist: rich (>=13.9.4,<15.0.0)
Requires-Dist: tqdm (>=4.67.1,<5.0.0)
Requires-Dist: yfinance (>=0.2.55,<0.3.0)
Requires-Dist: zstandard (>=0.23.0,<0.24.0)
Project-URL: Documentation, https://pfeed-docs.pfund.ai
Project-URL: Homepage, https://pfund.ai
Project-URL: Repository, https://github.com/PFund-Software-Ltd/pfeed
